[
  {
    "mainPlatform": "tweet",
    "summary": "Simon, re: Old UI Concept",
    "mainText": "'It was never implemented I’m pretty sure, will do something similar post launch'",
    "date": "12 17 2025",
    "tags": [
      "Simon",
      "Future stuff",
      "Feature",
      "Simon Notes"
    ],
    "sources": [
      {
        "1": [
          "tweet by Simon",
          "https://xcancel.com/Simon_Hypixel/status/2001450075520741799?s=20"
        ]
      }
    ]
  },
  {
    "mainPlatform": "tweet",
    "summary": "Buddha, re: LANgeek getting a Creator Code",
    "mainText": "'🫡❤️'",
    "date": "12 17 2025",
    "tags": [
      "BuddhaCat",
      "Community"
    ],
    "sources": [
      {
        "1": [
          "tweet by BuddhaCat",
          "https://xcancel.com/ItsBuddhaCat/status/2001390219971494175?s=20"
        ]
      }
    ]
  },
  {
    "mainPlatform": "tweet",
    "summary": "Buddha, re: HatsuyaDev getting a Creator Code",
    "mainText": "' '\n\n(Cat Flashing Heart - Gif)",
    "date": "12 17 2025",
    "tags": [
      "BuddhaCat",
      "Community"
    ],
    "sources": [
      {
        "1": [
          "tweet by BuddhaCat",
          "https://xcancel.com/ItsBuddhaCat/status/2001390135741493588?s=20"
        ]
      }
    ]
  },
  {
    "mainPlatform": "tweet",
    "summary": "Buddha, re: MuffledMuffin bumping their application",
    "mainText": "'sent :)'\n\n(Lean In, Thumbs Up - Gif)",
    "date": "12 17 2025",
    "tags": [
      "BuddhaCat",
      "Community"
    ],
    "sources": [
      {
        "1": [
          "tweet by BuddhaCat",
          "https://xcancel.com/ItsBuddhaCat/status/2001388388331487648?s=20"
        ]
      }
    ]
  },
  {
    "mainPlatform": "tweet",
    "summary": "Buddha, re: MuffledMuffin bumping their application",
    "mainText": "'checking now :)'",
    "date": "12 17 2025",
    "tags": [
      "BuddhaCat",
      "Community"
    ],
    "sources": [
      {
        "1": [
          "tweet by BuddhaCat",
          "https://xcancel.com/ItsBuddhaCat/status/2001387620740350381?s=20"
        ]
      }
    ]
  },
  {
    "mainPlatform": "tweet",
    "summary": "Oscar streaming",
    "mainText": "'twitch.tv/ogrpgmusic making music live now!'",
    "date": "12 17 2025",
    "tags": [
      "Oscar Garvin",
      "Music"
    ],
    "sources": [
      {
        "1": [
          "tweet by Oscar Garvin",
          "https://xcancel.com/onpujam/status/2001383467242733875?s=20"
        ]
      }
    ]
  },
  {
    "mainPlatform": "tweet",
    "summary": "Oscar streaming",
    "mainText": "'Streaming music production in 30mins over at http://twitch.tv/OGRPGmusic (not Hytale music)'",
    "date": "12 17 2025",
    "tags": [
      "Oscar Garvin",
      "Music"
    ],
    "sources": [
      {
        "1": [
          "tweet by Oscar Garvin",
          "https://xcancel.com/onpujam/status/2001373991240663079?s=20"
        ]
      }
    ]
  },
  {
    "mainPlatform": "tweet",
    "summary": "Oscar, re: LegitHytaleLeaks saying users will slowly age IRL when they play Hytale",
    "mainText": "'Not if you reverse aging like Bryan Johnson'",
    "date": "12 17 2025",
    "tags": [
      "Oscar Garvin",
      "Community"
    ],
    "sources": [
      {
        "1": [
          "tweet by Oscar Garvin",
          "https://xcancel.com/onpujam/status/2001354767105474741?s=20"
        ]
      }
    ]
  },
  {
    "mainPlatform": "tweet",
    "summary": "Slikey, re: Molina asking if Hytale could have a pre-load",
    "mainText": "'No pre-load. That would require more system to be built to decrypt downloads etc. We don't have capacity for it.'",
    "date": "12 17 2025",
    "tags": [
      "Slikey",
      "Tech"
    ],
    "sources": [
      {
        "1": [
          "tweet by Slikey",
          "https://xcancel.com/slikey/status/2001353149270171731?s=20"
        ]
      }
    ]
  },
  {
    "mainPlatform": "tweet",
    "summary": "Slikey, re: potential for OAuth 2.0 system that external developers can use",
    "mainText": "'Not for launch, we need to evaluate the use-cases and potential impact to privacy, child protection & security. We understand the value it would provide to third-party websites that want to offer out-of-game experiences.'",
    "date": "12 17 2025",
    "tags": [
      "Slikey",
      "Server",
      "Tech"
    ],
    "sources": [
      {
        "1": [
          "tweet by Slikey",
          "https://xcancel.com/slikey/status/2001338452135309698?s=20"
        ]
      }
    ]
  },
  {
    "mainPlatform": "tweet",
    "summary": "Buddha, re: HytaleFR getting Creator Code",
    "mainText": "'lets gooooo'",
    "date": "12 17 2025",
    "tags": [
      "BuddhaCat",
      "Community"
    ],
    "sources": [
      {
        "1": [
          "tweet by BuddhaCat",
          "https://xcancel.com/ItsBuddhaCat/status/2001338437023170568?s=20"
        ]
      }
    ]
  },
  {
    "mainPlatform": "tweet",
    "summary": "Buddha, re: Abelirre sending a Creator Program email",
    "mainText": "' '\n\n(Lean In, Thumbs Up - Gif)",
    "date": "12 17 2025",
    "tags": [
      "BuddhaCat",
      "Community"
    ],
    "sources": [
      {
        "1": [
          "tweet by BuddhaCat",
          "https://xcancel.com/ItsBuddhaCat/status/2001338300066599063?s=20"
        ]
      }
    ]
  },
  {
    "mainPlatform": "tweet",
    "summary": "Buddha, re: Xaffiri apologizing for Creator Program Application Emails",
    "mainText": "'It's honestly my pleasure 🫡 I live to serve this community!'",
    "date": "12 17 2025",
    "tags": [
      "BuddhaCat",
      "Community"
    ],
    "sources": [
      {
        "1": [
          "tweet by BuddhaCat",
          "https://xcancel.com/ItsBuddhaCat/status/2001305109926457569?s=20"
        ]
      }
    ]
  },
  {
    "mainPlatform": "tweet",
    "summary": "Buddha, re: Zeusley bumping his creator code email",
    "mainText": "'Just sent your form <3 (thank you for you bumping it - my inbox is exploding lmao)'",
    "date": "12 17 2025",
    "tags": [
      "BuddhaCat",
      "Community"
    ],
    "sources": [
      {
        "1": [
          "tweet by BuddhaCat",
          "https://xcancel.com/ItsBuddhaCat/status/2001304484220121250?s=20"
        ]
      }
    ]
  },
  {
    "mainPlatform": "tweet",
    "summary": "DevSlashNull, re: LegitHytaleLeaks saying Hytale won't affect Male Pattern Baldness",
    "mainText": "'Hair do just be falling out'",
    "date": "12 17 2025",
    "tags": [
      "DevSlashNull",
      "Community",
      "Off Topic"
    ],
    "sources": [
      {
        "1": [
          "tweet by DevSlashNull",
          "https://xcancel.com/DevSlashNulled/status/2001297442810015795?s=20"
        ]
      }
    ]
  },
  {
    "mainPlatform": "tweet",
    "summary": "Buddha, re: MuffledMuffin wondering how many Creator Program applications Buddha is reviewing",
    "mainText": "'\"Hey BuddhaCat what is your day-to-day like?!\"'\n\n(Sweaty Guy Typing Furiously - Gif)",
    "date": "12 17 2025",
    "tags": [
      "BuddhaCat",
      "Community"
    ],
    "sources": [
      {
        "1": [
          "tweet by BuddhaCat",
          "https://xcancel.com/ItsBuddhaCat/status/2001295012751892918?s=20"
        ]
      }
    ]
  },
  {
    "mainPlatform": "tweet",
    "summary": "Buddha, re: Training Dummies have been shown before",
    "mainText": "'This is true!'",
    "date": "12 17 2025",
    "tags": [
      "BuddhaCat",
      "Feature"
    ],
    "sources": [
      {
        "1": [
          "tweet by BuddhaCat",
          "https://xcancel.com/ItsBuddhaCat/status/2001294654667464714?s=20"
        ]
      }
    ]
  },
  {
    "mainPlatform": "tweet",
    "summary": "Buddha, re: Creator requesting Creator Code",
    "mainText": "'Replied, my friend 🫡'",
    "date": "12 17 2025",
    "tags": [
      "BuddhaCat",
      "Community"
    ],
    "sources": [
      {
        "1": [
          "tweet by BuddhaCat",
          "https://xcancel.com/ItsBuddhaCat/status/2001294396453503399?s=20"
        ]
      }
    ]
  },
  {
    "mainPlatform": "tweet",
    "summary": "Thomas, re: Hawkon joking about the devs balding from stress",
    "mainText": "'I for sure gained a bunch of grey hair past years'",
    "date": "12 17 2025",
    "tags": [
      "Thomas Frick",
      "Community",
      "Devs",
      "Off Topic"
    ],
    "sources": [
      {
        "1": [
          "tweet by Thomas Frick",
          "https://xcancel.com/ThomasFrick/status/2001266843856888108?s=20"
        ]
      }
    ]
  },
  {
    "mainPlatform": "tweet",
    "summary": "Oscar, re: why the 'Fear' track in the OST is so scarry",
    "mainText": "'You'll see🙂'",
    "date": "12 17 2025",
    "tags": [
      "Oscar Garvin",
      "Music",
      "Hints"
    ],
    "sources": [
      {
        "1": [
          "tweet by Oscar Garvin",
          "https://xcancel.com/onpujam/status/2001250458577645791?s=20"
        ]
      }
    ]
  },
  {
    "mainPlatform": "tweet",
    "summary": "Oscar, re: keyboard autocorrect challenge",
    "mainText": "'\"Woah\". I guess my keyboard didn't expect that.'",
    "date": "12 17 2025",
    "tags": [
      "Oscar Garvin",
      "Community"
    ],
    "sources": [
      {
        "1": [
          "tweet by Oscar Garvin",
          "https://xcancel.com/onpujam/status/2001249264513712263?s=20"
        ]
      }
    ]
  },
  {
    "mainPlatform": "tweet",
    "summary": "Oscar, re: LegitHytaleLeaks saying Scott Cawthon won't be involved in Hytale",
    "mainText": "'Now do a post each about all the other ones that also aren't involved 🤪 see you when Half-Life 3 releases'",
    "date": "12 17 2025",
    "tags": [
      "Oscar Garvin",
      "Community"
    ],
    "sources": [
      {
        "1": [
          "tweet by Oscar Garvin",
          "https://xcancel.com/onpujam/status/2001248529520714217?s=20"
        ]
      }
    ]
  },
  {
    "mainPlatform": "tweet",
    "summary": "Zero, re: using gitlab",
    "mainText": "'Yeah but its been many years so I'm sure a lot has changed'",
    "date": "12 17 2025",
    "tags": [
      "Zero",
      "Tech"
    ],
    "sources": [
      {
        "1": [
          "tweet by Zero",
          "https://xcancel.com/ZeroErrors/status/2001240772071579753?s=20"
        ]
      }
    ]
  },
  {
    "mainPlatform": "tweet",
    "summary": "Mewen, re: fanart",
    "mainText": "'Love the concept!'",
    "date": "12 17 2025",
    "tags": [
      "Mewen",
      "Community",
      "Art"
    ],
    "sources": [
      {
        "1": [
          "tweet by Mewen",
          "https://xcancel.com/MewSoul/status/2001195766233137421?s=20"
        ]
      }
    ]
  },
  {
    "mainPlatform": "tweet",
    "summary": "Slikey, re: server plugin dev asking for information",
    "mainText": "'It starts January 13 - if we were to now partially release the game, it wouldn't help anyone truly, create more noise for us and in the end result in more frustrations. There is no reason for FOMO on such a new ecosystem where everyone has to learn from scratch.'",
    "date": "12 16 2025",
    "tags": [
      "Slikey",
      "Server",
      "Tech",
      "Community"
    ],
    "sources": [
      {
        "1": [
          "tweet by Slikey",
          "https://xcancel.com/slikey/status/2001170430074191993?s=20"
        ]
      }
    ]
  },
  {
    "mainPlatform": "tweet",
    "summary": "Simon, re: fanart",
    "mainText": "'Incredible art! Love it!'",
    "date": "12 16 2025",
    "tags": [
      "Simon",
      "Community",
      "Art"
    ],
    "sources": [
      {
        "1": [
          "tweet by Simon",
          "https://xcancel.com/Simon_Hypixel/status/2001160072332784019?s=20"
        ]
      }
    ]
  },
  {
    "mainPlatform": "tweet",
    "summary": "Slikey, re: physics engine via mods in Minecraft",
    "mainText": "'You mean the work @RyanHCode has been doing?'",
    "date": "12 16 2025",
    "tags": [
      "Slikey",
      "Modding",
      "Feature",
      "Future stuff"
    ],
    "sources": [
      {
        "1": [
          "tweet by Slikey",
          "https://xcancel.com/slikey/status/2001111042240249909?s=20"
        ]
      }
    ]
  },
  {
    "mainPlatform": "tweet",
    "summary": "Oscar, re: Hawkon making a Discord",
    "mainText": "' '\n\n(Let Me In - Gif)",
    "date": "12 16 2025",
    "tags": [
      "Oscar Garvin",
      "Community"
    ],
    "sources": [
      {
        "1": [
          "tweet by Oscar Garvin",
          "https://xcancel.com/onpujam/status/2001109131000725715?s=20"
        ]
      }
    ]
  },
  {
    "mainPlatform": "tweet",
    "summary": "Oscar, re: user unable to locate a track",
    "mainText": "'Genesis, it should be in the portfolio 1'",
    "date": "12 16 2025",
    "tags": [
      "Oscar Garvin",
      "Music",
      "Community"
    ],
    "sources": [
      {
        "1": [
          "tweet by Oscar Garvin",
          "https://xcancel.com/onpujam/status/2001108775441256606?s=20"
        ]
      }
    ]
  },
  {
    "mainPlatform": "tweet",
    "summary": "Oscar, re: fan Hytale track",
    "mainText": "'That's nice! I'd suggest adding a layer of bass underneath 😁 that would really round it out'",
    "date": "12 16 2025",
    "tags": [
      "Oscar Garvin",
      "Music",
      "Community"
    ],
    "sources": [
      {
        "1": [
          "tweet by Oscar Garvin",
          "https://xcancel.com/onpujam/status/2001108357432627649?s=20"
        ]
      }
    ]
  },
  {
    "mainPlatform": "tweet",
    "summary": "Oscar, re: user describing what those two tracks sound like",
    "mainText": "'You're right to point that out. I find the retro sounds from the 80s, 90s, 00s really endearing and love using it in my music! I just can't regularly do so in the mostly orchestral OST of Hytale, but that doesn't stop me from trying whenever I can 😜 including jazzy stuff.'",
    "date": "12 16 2025",
    "tags": [
      "Oscar Garvin",
      "Music",
      "Community"
    ],
    "sources": [
      {
        "1": [
          "tweet by Oscar Garvin",
          "https://xcancel.com/onpujam/status/2001108062107468182?s=20"
        ]
      }
    ]
  }
]