[
    {
        "news": [
            "Statement",
            "Simon",
            "Update",
            "Blog",
            "Tweet",
            "Post-Cancellation",
            "Community",
            "Modding",
            "Business",
            "Early Access",
            "Lore",
            "Features",
            "Engine",
            "Servers"
        ]
    },
    {
        "community": [
            "Announcement",
            "Website"
        ]
    },
    {
        "colors": [
            {
                "Statement": [
                    "#FA8F8F",
                    "black"
                ],
                "Simon": [
                    "#57C2F7",
                    "black"
                ]
            }
        ]
    }
]
